{
  "annotations": {
    "list": [
      {
        "builtIn": 1,
        "datasource": "Prometheus",
        "enable": true,
        "hide": true,
        "iconColor": "rgba(0, 211, 255, 1)",
        "name": "Annotations & Alerts",
        "type": "dashboard"
      },
      {
        "datasource": "Prometheus",
        "enable": true,
        "expr": "changes(vendor:coherence_cluster_size{cluster=~\"$ClusterName\"}[1m])",
        "hide": false,
        "iconColor": "rgba(255, 96, 96, 1)",
        "limit": 100,
        "name": "Show Cluster Size Changes",
        "showIn": 0,
        "tagKeys": "cluster",
        "tags": [],
        "textFormat": "",
        "titleFormat": "Cluster Size Changed.",
        "type": "tags",
        "useValueForTime": false
      },
      {
        "datasource": "Prometheus",
        "enable": true,
        "expr": "changes(vendor:coherence_service_owned_partitions_primary{cluster=~\"$ClusterName\"}[60s])",
        "hide": false,
        "iconColor": "rgba(255, 96, 96, 1)",
        "limit": 100,
        "name": "Show Partition Transfers",
        "showIn": 0,
        "tagKeys": "name",
        "tags": [],
        "titleFormat": "Partition Transfers",
        "type": "tags"
      }
    ]
  },
  "editable": true,
  "gnetId": null,
  "graphTooltip": 0,
  "id": 29,
  "iteration": 1592180305423,
  "links": [
    {
      "icon": "dashboard",
      "includeVars": true,
      "keepTime": true,
      "tags": [],
      "title": "Manage Alerts",
      "tooltip": "",
      "type": "link",
      "url": "/d/coh-alerts"
    },
    {
      "asDropdown": true,
      "icon": "external link",
      "includeVars": true,
      "keepTime": true,
      "tags": [
        "dashboard"
      ],
      "title": "Available Dashboards",
      "type": "dashboards"
    }
  ],
  "panels": [
    {
      "content": "<center><h3>Cluster Overview - $CoherenceVersion</h3></center>",
      "datasource": "Prometheus",
      "gridPos": {
        "h": 2,
        "w": 24,
        "x": 0,
        "y": 0
      },
      "id": 101,
      "links": [],
      "mode": "html",
      "title": "",
      "type": "text"
    },
    {
      "collapsed": true,
      "datasource": "Prometheus",
      "gridPos": {
        "h": 1,
        "w": 24,
        "x": 0,
        "y": 2
      },
      "id": 111,
      "panels": [
        {
          "dashboardFilter": "",
          "dashboardTags": [],
          "folderId": null,
          "gridPos": {
            "h": 6,
            "w": 12,
            "x": 0,
            "y": 3
          },
          "id": 106,
          "limit": 10,
          "links": [],
          "nameFilter": "",
          "onlyAlertsOnDashboard": false,
          "show": "current",
          "sortOrder": 1,
          "stateFilter": [
            "alerting"
          ],
          "title": "Current Alerts",
          "type": "alertlist"
        },
        {
          "dashboardFilter": "",
          "dashboardTags": [],
          "folderId": null,
          "gridPos": {
            "h": 6,
            "w": 12,
            "x": 12,
            "y": 3
          },
          "id": 107,
          "limit": 10,
          "links": [],
          "nameFilter": "",
          "onlyAlertsOnDashboard": false,
          "show": "changes",
          "sortOrder": 1,
          "stateFilter": [
            "alerting"
          ],
          "title": "Recent Alert State Changes",
          "type": "alertlist"
        }
      ],
      "title": "Alerts",
      "type": "row"
    },
    {
      "collapsed": false,
      "datasource": "Prometheus",
      "gridPos": {
        "h": 1,
        "w": 24,
        "x": 0,
        "y": 3
      },
      "id": 109,
      "panels": [],
      "title": "Cluster Overview - $ClusterName",
      "type": "row"
    },
    {
      "cacheTimeout": null,
      "colorBackground": false,
      "colorValue": false,
      "colors": [
        "#299c46",
        "rgba(237, 129, 40, 0.89)",
        "#d44a3a"
      ],
      "datasource": "Prometheus",
      "description": "Shows the number of cluster members.",
      "format": "none",
      "gauge": {
        "maxValue": 100,
        "minValue": 0,
        "show": false,
        "thresholdLabels": false,
        "thresholdMarkers": true
      },
      "gridPos": {
        "h": 5,
        "w": 4,
        "x": 0,
        "y": 4
      },
      "id": 95,
      "interval": null,
      "links": [
        {
          "title": "Members Summary Dashboard",
          "url": "/d/coh-members-summary/members-summary-dashboard?$__url_time_range&$__all_variables"
        }
      ],
      "mappingType": 1,
      "mappingTypes": [
        {
          "name": "value to text",
          "value": 1
        },
        {
          "name": "range to text",
          "value": 2
        }
      ],
      "maxDataPoints": 100,
      "nullPointMode": "connected",
      "nullText": null,
      "postfix": "",
      "postfixFontSize": "50%",
      "prefix": "",
      "prefixFontSize": "50%",
      "rangeMaps": [
        {
          "from": "null",
          "text": "N/A",
          "to": "null"
        }
      ],
      "sparkline": {
        "fillColor": "rgba(31, 118, 189, 0.18)",
        "full": false,
        "lineColor": "rgb(31, 120, 193)",
        "show": false
      },
      "tableColumn": "",
      "targets": [
        {
          "expr": "count(vendor:coherence_cluster_size{cluster=~\"$ClusterName\"})  ",
          "format": "time_series",
          "instant": true,
          "intervalFactor": 1,
          "refId": "A"
        }
      ],
      "thresholds": "",
      "timeFrom": null,
      "timeShift": null,
      "title": "Cluster Members",
      "type": "singlestat",
      "valueFontSize": "80%",
      "valueMaps": [
        {
          "op": "=",
          "text": "N/A",
          "value": "null"
        }
      ],
      "valueName": "current"
    },
    {
      "cacheTimeout": null,
      "colorBackground": false,
      "colorValue": true,
      "colors": [
        "#299c46",
        "rgba(237, 129, 40, 0.89)",
        "#d44a3a"
      ],
      "datasource": "Prometheus",
      "decimals": 0,
      "description": "Recent member departures.",
      "format": "none",
      "gauge": {
        "maxValue": 100,
        "minValue": 0,
        "show": false,
        "thresholdLabels": false,
        "thresholdMarkers": true
      },
      "gridPos": {
        "h": 5,
        "w": 4,
        "x": 4,
        "y": 4
      },
      "id": 80,
      "interval": null,
      "links": [],
      "mappingType": 1,
      "mappingTypes": [
        {
          "name": "value to text",
          "value": 1
        },
        {
          "name": "range to text",
          "value": 2
        }
      ],
      "maxDataPoints": 100,
      "nullPointMode": "connected",
      "nullText": null,
      "postfix": "",
      "postfixFontSize": "50%",
      "prefix": "",
      "prefixFontSize": "50%",
      "rangeMaps": [
        {
          "from": "null",
          "text": "N/A",
          "to": "null"
        }
      ],
      "sparkline": {
        "fillColor": "rgba(31, 118, 189, 0.18)",
        "full": false,
        "lineColor": "rgb(31, 120, 193)",
        "show": false
      },
      "tableColumn": "",
      "targets": [
        {
          "expr": "avg(delta(vendor:coherence_cluster_members_departure_count{cluster=~\"$ClusterName\"}[5m])) >= 0",
          "format": "time_series",
          "instant": true,
          "intervalFactor": 1,
          "legendFormat": "",
          "refId": "A"
        }
      ],
      "thresholds": "0.5,2",
      "timeFrom": null,
      "timeShift": null,
      "title": "Recent Departures",
      "type": "singlestat",
      "valueFontSize": "80%",
      "valueMaps": [
        {
          "op": "=",
          "text": "N/A",
          "value": "null"
        }
      ],
      "valueName": "current"
    },
    {
      "cacheTimeout": null,
      "colorBackground": false,
      "colorValue": true,
      "colors": [
        "#299c46",
        "rgba(237, 129, 40, 0.89)",
        "#d44a3a"
      ],
      "datasource": "Prometheus",
      "decimals": 0,
      "description": "The number of services with endangered partitions.",
      "format": "none",
      "gauge": {
        "maxValue": 100,
        "minValue": 0,
        "show": false,
        "thresholdLabels": false,
        "thresholdMarkers": true
      },
      "gridPos": {
        "h": 5,
        "w": 4,
        "x": 8,
        "y": 4
      },
      "id": 92,
      "interval": null,
      "links": [
        {
          "title": "Services Summary Dashboard",
          "url": "/d/coh-services-summary/services-summary-dashboard?$__url_time_range&$__all_variables"
        }
      ],
      "mappingType": 1,
      "mappingTypes": [
        {
          "name": "value to text",
          "value": 1
        },
        {
          "name": "range to text",
          "value": 2
        }
      ],
      "maxDataPoints": 100,
      "nullPointMode": "connected",
      "nullText": null,
      "postfix": "",
      "postfixFontSize": "50%",
      "prefix": "",
      "prefixFontSize": "50%",
      "rangeMaps": [
        {
          "from": "null",
          "text": "N/A",
          "to": "null"
        }
      ],
      "sparkline": {
        "fillColor": "rgba(31, 118, 189, 0.18)",
        "full": false,
        "lineColor": "rgb(31, 120, 193)",
        "show": false
      },
      "tableColumn": "",
      "targets": [
        {
          "expr": "count(vendor:coherence_partition_assignment_ha_status_code{cluster=~\"$ClusterName\"} <= 1)",
          "format": "time_series",
          "instant": true,
          "interval": "",
          "intervalFactor": 1,
          "legendFormat": "",
          "refId": "A"
        }
      ],
      "thresholds": "1,2",
      "timeFrom": null,
      "timeShift": null,
      "title": "Endangered Services",
      "type": "singlestat",
      "valueFontSize": "80%",
      "valueMaps": [
        {
          "op": "=",
          "text": "0",
          "value": "null"
        }
      ],
      "valueName": "current"
    },
    {
      "cacheTimeout": null,
      "colorBackground": false,
      "colorValue": false,
      "colors": [
        "#299c46",
        "rgba(237, 129, 40, 0.89)",
        "#d44a3a"
      ],
      "datasource": "Prometheus",
      "description": "Total used cluster heap across all members.",
      "format": "decbytes",
      "gauge": {
        "maxValue": 100,
        "minValue": 0,
        "show": false,
        "thresholdLabels": false,
        "thresholdMarkers": true
      },
      "gridPos": {
        "h": 5,
        "w": 4,
        "x": 12,
        "y": 4
      },
      "id": 55,
      "interval": null,
      "links": [],
      "mappingType": 1,
      "mappingTypes": [
        {
          "name": "value to text",
          "value": 1
        },
        {
          "name": "range to text",
          "value": 2
        }
      ],
      "maxDataPoints": 100,
      "nullPointMode": "connected",
      "nullText": null,
      "postfix": "",
      "postfixFontSize": "50%",
      "prefix": "",
      "prefixFontSize": "50%",
      "rangeMaps": [
        {
          "from": "null",
          "text": "N/A",
          "to": "null"
        }
      ],
      "sparkline": {
        "fillColor": "rgba(31, 118, 189, 0.18)",
        "full": false,
        "lineColor": "rgb(31, 120, 193)",
        "show": true
      },
      "tableColumn": "",
      "targets": [
        {
          "expr": "sum(vendor:coherence_memory_heap_after_gc_used{cluster=~\"$ClusterName\"})",
          "format": "time_series",
          "instant": true,
          "intervalFactor": 1,
          "legendFormat": "",
          "refId": "A"
        }
      ],
      "thresholds": "",
      "title": "Used Cluster Heap After GC",
      "type": "singlestat",
      "valueFontSize": "80%",
      "valueMaps": [
        {
          "op": "=",
          "text": "N/A",
          "value": "null"
        }
      ],
      "valueName": "current"
    },
    {
      "cacheTimeout": null,
      "colorBackground": false,
      "colorValue": false,
      "colors": [
        "#299c46",
        "rgba(237, 129, 40, 0.89)",
        "#d44a3a"
      ],
      "datasource": "Prometheus",
      "description": "Total available cluster heap across all members.",
      "format": "decbytes",
      "gauge": {
        "maxValue": 100,
        "minValue": 0,
        "show": false,
        "thresholdLabels": false,
        "thresholdMarkers": true
      },
      "gridPos": {
        "h": 5,
        "w": 4,
        "x": 16,
        "y": 4
      },
      "id": 38,
      "interval": null,
      "links": [],
      "mappingType": 1,
      "mappingTypes": [
        {
          "name": "value to text",
          "value": 1
        },
        {
          "name": "range to text",
          "value": 2
        }
      ],
      "maxDataPoints": 100,
      "nullPointMode": "connected",
      "nullText": null,
      "postfix": "",
      "postfixFontSize": "50%",
      "prefix": "",
      "prefixFontSize": "50%",
      "rangeMaps": [
        {
          "from": "null",
          "text": "N/A",
          "to": "null"
        }
      ],
      "sparkline": {
        "fillColor": "rgba(31, 118, 189, 0.18)",
        "full": false,
        "lineColor": "rgb(31, 120, 193)",
        "show": true
      },
      "tableColumn": "",
      "targets": [
        {
          "expr": "sum(vendor:coherence_memory_heap_memory_usage_max{cluster=~\"$ClusterName\"})",
          "format": "time_series",
          "instant": true,
          "intervalFactor": 1,
          "refId": "A"
        }
      ],
      "thresholds": "",
      "title": "Total Cluster Heap",
      "type": "singlestat",
      "valueFontSize": "80%",
      "valueMaps": [
        {
          "op": "=",
          "text": "N/A",
          "value": "null"
        }
      ],
      "valueName": "current"
    },
    {
      "cacheTimeout": null,
      "colorBackground": false,
      "colorValue": false,
      "colors": [
        "#299c46",
        "rgba(237, 129, 40, 0.89)",
        "#d44a3a"
      ],
      "datasource": "Prometheus",
      "decimals": 1,
      "description": "Percentage of heap memory used after GC across all members.",
      "format": "percent",
      "gauge": {
        "maxValue": 100,
        "minValue": 0,
        "show": true,
        "thresholdLabels": true,
        "thresholdMarkers": true
      },
      "gridPos": {
        "h": 5,
        "w": 4,
        "x": 20,
        "y": 4
      },
      "id": 9,
      "interval": null,
      "links": [],
      "mappingType": 1,
      "mappingTypes": [
        {
          "name": "value to text",
          "value": 1
        },
        {
          "name": "range to text",
          "value": 2
        }
      ],
      "maxDataPoints": 100,
      "nullPointMode": "connected",
      "nullText": null,
      "postfix": "",
      "postfixFontSize": "50%",
      "prefix": "",
      "prefixFontSize": "50%",
      "rangeMaps": [
        {
          "from": "null",
          "text": "N/A",
          "to": "null"
        }
      ],
      "sparkline": {
        "fillColor": "rgba(31, 118, 189, 0.18)",
        "full": false,
        "lineColor": "rgb(31, 120, 193)",
        "show": false
      },
      "tableColumn": "",
      "targets": [
        {
          "expr": "sum(vendor:coherence_memory_heap_after_gc_used{cluster=~\"$ClusterName\"}) / sum(vendor:coherence_memory_heap_memory_usage_max{cluster=~\"$ClusterName\"}) * 100  ",
          "format": "time_series",
          "instant": true,
          "intervalFactor": 1,
          "legendFormat": "",
          "refId": "A"
        }
      ],
      "thresholds": "50,80",
      "timeFrom": null,
      "title": "Total Memory Usage %",
      "type": "singlestat",
      "valueFontSize": "80%",
      "valueMaps": [
        {
          "op": "=",
          "text": "N/A",
          "value": "null"
        }
      ],
      "valueName": "current"
    },
    {
      "aliasColors": {},
      "bars": false,
      "dashLength": 10,
      "dashes": false,
      "datasource": "Prometheus",
      "description": "Total and used cluster memory across all members (storage enabled and disabled). Please see tables and graphs directly below for breakdown by Role.",
      "fill": 1,
      "fillGradient": 0,
      "gridPos": {
        "h": 8,
        "w": 12,
        "x": 0,
        "y": 9
      },
      "hiddenSeries": false,
      "id": 14,
      "legend": {
        "alignAsTable": true,
        "avg": false,
        "current": true,
        "max": true,
        "min": false,
        "show": true,
        "total": false,
        "values": true
      },
      "lines": true,
      "linewidth": 1,
      "links": [],
      "nullPointMode": "null",
      "options": {
        "dataLinks": []
      },
      "percentage": false,
      "pointradius": 5,
      "points": false,
      "renderer": "flot",
      "seriesOverrides": [],
      "spaceLength": 10,
      "stack": false,
      "steppedLine": false,
      "targets": [
        {
          "expr": "sum(vendor:coherence_memory_heap_after_gc_used{cluster=~\"$ClusterName\"})",
          "format": "time_series",
          "interval": "",
          "intervalFactor": 1,
          "legendFormat": "Used Cluster Memory After GC",
          "refId": "A"
        },
        {
          "expr": "sum(vendor:coherence_memory_heap_memory_usage_max{cluster=~\"$ClusterName\"})",
          "format": "time_series",
          "interval": "",
          "intervalFactor": 1,
          "legendFormat": "Total Cluster Memory",
          "refId": "B"
        }
      ],
      "thresholds": [],
      "timeFrom": null,
      "timeRegions": [],
      "timeShift": null,
      "title": "Cluster Memory Details",
      "tooltip": {
        "shared": true,
        "sort": 0,
        "value_type": "individual"
      },
      "type": "graph",
      "xaxis": {
        "buckets": null,
        "mode": "time",
        "name": null,
        "show": true,
        "values": []
      },
      "yaxes": [
        {
          "format": "decbytes",
          "label": null,
          "logBase": 1,
          "max": null,
          "min": null,
          "show": true
        },
        {
          "format": "short",
          "label": null,
          "logBase": 1,
          "max": null,
          "min": null,
          "show": false
        }
      ],
      "yaxis": {
        "align": false,
        "alignLevel": null
      }
    },
    {
      "aliasColors": {},
      "bars": false,
      "dashLength": 10,
      "dashes": false,
      "datasource": "Prometheus",
      "description": "Show the current load average across all machines.",
      "fill": 1,
      "fillGradient": 0,
      "gridPos": {
        "h": 8,
        "w": 12,
        "x": 12,
        "y": 9
      },
      "hiddenSeries": false,
      "id": 15,
      "legend": {
        "alignAsTable": false,
        "avg": false,
        "current": true,
        "max": false,
        "min": false,
        "rightSide": false,
        "show": true,
        "total": false,
        "values": true
      },
      "lines": true,
      "linewidth": 1,
      "links": [
        {
          "title": "Machines Summary Dashboard",
          "url": "/d/coh-machines-summary/machines-summary-dashboard?$__url_time_range&$__all_variables"
        }
      ],
      "nullPointMode": "null",
      "options": {
        "dataLinks": []
      },
      "percentage": false,
      "pointradius": 5,
      "points": false,
      "renderer": "flot",
      "seriesOverrides": [],
      "spaceLength": 10,
      "stack": true,
      "steppedLine": false,
      "targets": [
        {
          "expr": "avg(vendor:coherence_os_system_load_average{cluster=~\"$ClusterName\"}) by (machine)",
          "format": "time_series",
          "instant": false,
          "interval": "",
          "intervalFactor": 1,
          "legendFormat": "{{machine}}",
          "refId": "B"
        }
      ],
      "thresholds": [],
      "timeFrom": null,
      "timeRegions": [],
      "timeShift": null,
      "title": "Current Load Averages",
      "tooltip": {
        "shared": true,
        "sort": 0,
        "value_type": "individual"
      },
      "type": "graph",
      "xaxis": {
        "buckets": null,
        "mode": "time",
        "name": null,
        "show": true,
        "values": []
      },
      "yaxes": [
        {
          "decimals": 2,
          "format": "short",
          "label": "",
          "logBase": 1,
          "max": null,
          "min": "0",
          "show": true
        },
        {
          "format": "short",
          "label": null,
          "logBase": 1,
          "max": null,
          "min": null,
          "show": false
        }
      ],
      "yaxis": {
        "align": false,
        "alignLevel": null
      }
    },
    {
      "columns": [],
      "datasource": "Prometheus",
      "description": "Total heap usage summarized by role.",
      "fontSize": "100%",
      "gridPos": {
        "h": 7,
        "w": 12,
        "x": 0,
        "y": 17
      },
      "id": 122,
      "links": [],
      "pageSize": null,
      "scroll": true,
      "showHeader": true,
      "sort": {
        "col": 0,
        "desc": true
      },
      "styles": [
        {
          "alias": "Time",
          "align": "auto",
          "dateFormat": "YYYY-MM-DD HH:mm:ss",
          "pattern": "Time",
          "type": "hidden"
        },
        {
          "alias": "Total Heap Used",
          "align": "auto",
          "colorMode": null,
          "colors": [
            "rgba(245, 54, 54, 0.9)",
            "rgba(237, 129, 40, 0.89)",
            "rgba(50, 172, 45, 0.97)"
          ],
          "dateFormat": "YYYY-MM-DD HH:mm:ss",
          "decimals": 2,
          "mappingType": 1,
          "pattern": "Value #A",
          "thresholds": [],
          "type": "number",
          "unit": "decbytes"
        },
        {
          "alias": "Total Heap Max",
          "align": "auto",
          "colorMode": null,
          "colors": [
            "rgba(245, 54, 54, 0.9)",
            "rgba(237, 129, 40, 0.89)",
            "rgba(50, 172, 45, 0.97)"
          ],
          "dateFormat": "YYYY-MM-DD HH:mm:ss",
          "decimals": 0,
          "mappingType": 1,
          "pattern": "Value #B",
          "thresholds": [],
          "type": "number",
          "unit": "decbytes"
        },
        {
          "alias": "Role",
          "align": "auto",
          "colorMode": null,
          "colors": [
            "rgba(245, 54, 54, 0.9)",
            "rgba(237, 129, 40, 0.89)",
            "rgba(50, 172, 45, 0.97)"
          ],
          "dateFormat": "YYYY-MM-DD HH:mm:ss",
          "decimals": 2,
          "mappingType": 1,
          "pattern": "role",
          "thresholds": [],
          "type": "string",
          "unit": "short"
        },
        {
          "alias": "Member Count",
          "align": "auto",
          "colorMode": null,
          "colors": [
            "rgba(245, 54, 54, 0.9)",
            "rgba(237, 129, 40, 0.89)",
            "rgba(50, 172, 45, 0.97)"
          ],
          "dateFormat": "YYYY-MM-DD HH:mm:ss",
          "decimals": 0,
          "mappingType": 1,
          "pattern": "Value #C",
          "thresholds": [],
          "type": "number",
          "unit": "short"
        },
        {
          "alias": "Total Heap Used %",
          "align": "auto",
          "colorMode": "value",
          "colors": [
            "rgba(50, 172, 45, 0.97)",
            "rgba(237, 129, 40, 0.89)",
            "rgba(245, 54, 54, 0.9)"
          ],
          "dateFormat": "YYYY-MM-DD HH:mm:ss",
          "decimals": 2,
          "mappingType": 1,
          "pattern": "Value #D",
          "thresholds": [
            ".5",
            ".8"
          ],
          "type": "number",
          "unit": "percentunit"
        },
        {
          "alias": "",
          "align": "auto",
          "colorMode": null,
          "colors": [
            "rgba(245, 54, 54, 0.9)",
            "rgba(237, 129, 40, 0.89)",
            "rgba(50, 172, 45, 0.97)"
          ],
          "decimals": 2,
          "pattern": "/.*/",
          "thresholds": [],
          "type": "number",
          "unit": "short"
        }
      ],
      "targets": [
        {
          "expr": "count(vendor:coherence_memory_heap_memory_usage_max{cluster=~\"$ClusterName\"}) by (role)",
          "format": "table",
          "instant": true,
          "intervalFactor": 1,
          "legendFormat": "",
          "refId": "C"
        },
        {
          "expr": "sum(vendor:coherence_memory_heap_after_gc_used{cluster=~\"$ClusterName\"}) by (role)",
          "format": "table",
          "instant": true,
          "intervalFactor": 1,
          "legendFormat": "",
          "refId": "A"
        },
        {
          "expr": "sum(vendor:coherence_memory_heap_memory_usage_max{cluster=~\"$ClusterName\"}) by (role)",
          "format": "table",
          "instant": true,
          "intervalFactor": 1,
          "legendFormat": "",
          "refId": "B"
        },
        {
          "expr": "sum(vendor:coherence_memory_heap_after_gc_used{cluster=~\"$ClusterName\"}) by (role) / sum(vendor:coherence_memory_heap_memory_usage_max{cluster=~\"$ClusterName\"}) by (role)  \n",
          "format": "table",
          "instant": true,
          "intervalFactor": 1,
          "legendFormat": "",
          "refId": "D"
        }
      ],
      "timeFrom": null,
      "timeShift": null,
      "title": "Total Heap Used By Role",
      "transform": "table",
      "type": "table"
    },
    {
      "aliasColors": {},
      "bars": false,
      "dashLength": 10,
      "dashes": false,
      "datasource": "Prometheus",
      "description": "Memory usage percentage by member role.",
      "fill": 1,
      "fillGradient": 0,
      "gridPos": {
        "h": 7,
        "w": 12,
        "x": 12,
        "y": 17
      },
      "hiddenSeries": false,
      "id": 120,
      "interval": "",
      "legend": {
        "alignAsTable": false,
        "avg": false,
        "current": true,
        "max": true,
        "min": false,
        "show": true,
        "total": false,
        "values": true
      },
      "lines": true,
      "linewidth": 1,
      "links": [],
      "nullPointMode": "null",
      "options": {
        "dataLinks": []
      },
      "percentage": false,
      "pointradius": 5,
      "points": false,
      "renderer": "flot",
      "seriesOverrides": [],
      "spaceLength": 10,
      "stack": false,
      "steppedLine": false,
      "targets": [
        {
          "expr": "sum(vendor:coherence_memory_heap_after_gc_used{cluster=~\"$ClusterName\"}) by (role) / sum(vendor:coherence_memory_heap_memory_usage_max{cluster=~\"$ClusterName\"}) by (role)  \n",
          "format": "time_series",
          "interval": "",
          "intervalFactor": 1,
          "legendFormat": "Role: {{role}}",
          "refId": "A"
        }
      ],
      "thresholds": [],
      "timeFrom": null,
      "timeRegions": [],
      "timeShift": null,
      "title": "Memory Usage % by Role",
      "tooltip": {
        "shared": true,
        "sort": 0,
        "value_type": "individual"
      },
      "type": "graph",
      "xaxis": {
        "buckets": null,
        "mode": "time",
        "name": null,
        "show": true,
        "values": []
      },
      "yaxes": [
        {
          "decimals": null,
          "format": "percentunit",
          "label": null,
          "logBase": 1,
          "max": "1",
          "min": "0",
          "show": true
        },
        {
          "format": "short",
          "label": null,
          "logBase": 1,
          "max": null,
          "min": null,
          "show": false
        }
      ],
      "yaxis": {
        "align": false,
        "alignLevel": null
      }
    },
    {
      "columns": [],
      "datasource": "Prometheus",
      "description": "The top  $TopLimit Members that have the lowest physical memory % available.",
      "fontSize": "100%",
      "gridPos": {
        "h": 6,
        "w": 8,
        "x": 0,
        "y": 24
      },
      "id": 104,
      "links": [],
      "pageSize": null,
      "scroll": true,
      "showHeader": true,
      "sort": {
        "col": 3,
        "desc": true
      },
      "styles": [
        {
          "alias": "Time",
          "align": "auto",
          "dateFormat": "YYYY-MM-DD HH:mm:ss",
          "pattern": "Time",
          "type": "hidden"
        },
        {
          "alias": "Free Physical Memory",
          "align": "auto",
          "colorMode": "value",
          "colors": [
            "rgba(245, 54, 54, 0.9)",
            "rgba(237, 129, 40, 0.89)",
            "rgba(50, 172, 45, 0.97)"
          ],
          "dateFormat": "YYYY-MM-DD HH:mm:ss",
          "decimals": 2,
          "mappingType": 1,
          "pattern": "Value",
          "thresholds": [
            ".80",
            ".50"
          ],
          "type": "number",
          "unit": "percentunit"
        },
        {
          "alias": "Machine",
          "align": "auto",
          "colorMode": null,
          "colors": [
            "rgba(245, 54, 54, 0.9)",
            "rgba(237, 129, 40, 0.89)",
            "rgba(50, 172, 45, 0.97)"
          ],
          "dateFormat": "YYYY-MM-DD HH:mm:ss",
          "decimals": 2,
          "link": true,
          "linkTooltip": "Drill down to machines summary",
          "linkUrl": "/d/coh-machines-summary?var-ClusterName=$ClusterName",
          "mappingType": 1,
          "pattern": "machine",
          "thresholds": [],
          "type": "number",
          "unit": "short"
        },
        {
          "alias": "",
          "align": "auto",
          "colorMode": null,
          "colors": [
            "rgba(245, 54, 54, 0.9)",
            "rgba(237, 129, 40, 0.89)",
            "rgba(50, 172, 45, 0.97)"
          ],
          "decimals": 2,
          "pattern": "/.*/",
          "thresholds": [],
          "type": "number",
          "unit": "short"
        }
      ],
      "targets": [
        {
          "expr": "bottomk($TopLimit, avg(vendor:coherence_os_free_physical_memory_size{cluster=~\"$ClusterName\"}/ vendor:coherence_os_total_physical_memory_size{cluster=~\"$ClusterName\"}) by (machine))",
          "format": "table",
          "instant": true,
          "interval": "",
          "intervalFactor": 1,
          "legendFormat": "",
          "refId": "A"
        }
      ],
      "title": "Top $TopLimit Machines -  Physical Memory",
      "transform": "table",
      "type": "table"
    },
    {
      "columns": [],
      "datasource": "Prometheus",
      "description": "The top  $TopLimit Members that have the highest CPU Load % over the current time range.",
      "fontSize": "100%",
      "gridPos": {
        "h": 6,
        "w": 8,
        "x": 8,
        "y": 24
      },
      "id": 103,
      "links": [],
      "pageSize": null,
      "scroll": true,
      "showHeader": true,
      "sort": {
        "col": 2,
        "desc": true
      },
      "styles": [
        {
          "alias": "Time",
          "align": "auto",
          "dateFormat": "YYYY-MM-DD HH:mm:ss",
          "pattern": "Time",
          "type": "hidden"
        },
        {
          "alias": "Member",
          "align": "auto",
          "colorMode": null,
          "colors": [
            "rgba(245, 54, 54, 0.9)",
            "rgba(237, 129, 40, 0.89)",
            "rgba(50, 172, 45, 0.97)"
          ],
          "dateFormat": "YYYY-MM-DD HH:mm:ss",
          "decimals": 2,
          "link": true,
          "linkTooltip": "Drill down to member details for ${__cell}",
          "linkUrl": "/d/coh-member-details?var-ClusterName=$ClusterName&var-MemberName=${__cell}",
          "mappingType": 1,
          "pattern": "member",
          "thresholds": [],
          "type": "string",
          "unit": "short"
        },
        {
          "alias": "Service",
          "align": "auto",
          "colorMode": null,
          "colors": [
            "rgba(245, 54, 54, 0.9)",
            "rgba(237, 129, 40, 0.89)",
            "rgba(50, 172, 45, 0.97)"
          ],
          "dateFormat": "YYYY-MM-DD HH:mm:ss",
          "decimals": 2,
          "mappingType": 1,
          "pattern": "name",
          "thresholds": [],
          "type": "string",
          "unit": "short"
        },
        {
          "alias": "Process CPU Load",
          "align": "auto",
          "colorMode": "value",
          "colors": [
            "rgba(50, 172, 45, 0.97)",
            "rgba(237, 129, 40, 0.89)",
            "rgba(245, 54, 54, 0.9)"
          ],
          "dateFormat": "YYYY-MM-DD HH:mm:ss",
          "decimals": 2,
          "mappingType": 1,
          "pattern": "Value",
          "thresholds": [
            ".5",
            ".8"
          ],
          "type": "number",
          "unit": "percentunit"
        },
        {
          "alias": "",
          "align": "auto",
          "colorMode": null,
          "colors": [
            "rgba(245, 54, 54, 0.9)",
            "rgba(237, 129, 40, 0.89)",
            "rgba(50, 172, 45, 0.97)"
          ],
          "decimals": 2,
          "pattern": "/.*/",
          "thresholds": [],
          "type": "number",
          "unit": "short"
        }
      ],
      "targets": [
        {
          "expr": "topk($TopLimit, sum(avg_over_time(vendor:coherence_os_process_cpu_load{cluster=~\"$ClusterName\"}[$__range] )) by (member))",
          "format": "table",
          "instant": true,
          "interval": "",
          "intervalFactor": 1,
          "legendFormat": "",
          "refId": "A"
        }
      ],
      "title": "Top $TopLimit Loaded Members  - Current Range",
      "transform": "table",
      "type": "table"
    },
    {
      "columns": [],
      "datasource": "Prometheus",
      "description": "The top  $TopLimit Members that have the highest heap memory % used over the current time range.",
      "fontSize": "100%",
      "gridPos": {
        "h": 6,
        "w": 8,
        "x": 16,
        "y": 24
      },
      "id": 102,
      "links": [],
      "pageSize": null,
      "scroll": true,
      "showHeader": true,
      "sort": {
        "col": 3,
        "desc": true
      },
      "styles": [
        {
          "alias": "Time",
          "align": "auto",
          "dateFormat": "YYYY-MM-DD HH:mm:ss",
          "pattern": "Time",
          "type": "hidden"
        },
        {
          "alias": "Member",
          "align": "auto",
          "colorMode": null,
          "colors": [
            "rgba(245, 54, 54, 0.9)",
            "rgba(237, 129, 40, 0.89)",
            "rgba(50, 172, 45, 0.97)"
          ],
          "dateFormat": "YYYY-MM-DD HH:mm:ss",
          "decimals": 2,
          "link": true,
          "linkTooltip": "Drill down to member details for  ${__cell}",
          "linkUrl": "/d/coh-member-details?var-ClusterName=$ClusterName&var-MemberName=${__cell}",
          "mappingType": 1,
          "pattern": "member",
          "thresholds": [],
          "type": "string",
          "unit": "short"
        },
        {
          "alias": "Service",
          "align": "auto",
          "colorMode": null,
          "colors": [
            "rgba(245, 54, 54, 0.9)",
            "rgba(237, 129, 40, 0.89)",
            "rgba(50, 172, 45, 0.97)"
          ],
          "dateFormat": "YYYY-MM-DD HH:mm:ss",
          "decimals": 2,
          "mappingType": 1,
          "pattern": "name",
          "thresholds": [],
          "type": "string",
          "unit": "short"
        },
        {
          "alias": "% Memory Used",
          "align": "auto",
          "colorMode": "value",
          "colors": [
            "rgba(50, 172, 45, 0.97)",
            "rgba(237, 129, 40, 0.89)",
            "rgba(245, 54, 54, 0.9)"
          ],
          "dateFormat": "YYYY-MM-DD HH:mm:ss",
          "decimals": 2,
          "mappingType": 1,
          "pattern": "Value",
          "thresholds": [
            ".50",
            ".80"
          ],
          "type": "number",
          "unit": "percentunit"
        },
        {
          "alias": "",
          "align": "auto",
          "colorMode": null,
          "colors": [
            "rgba(245, 54, 54, 0.9)",
            "rgba(237, 129, 40, 0.89)",
            "rgba(50, 172, 45, 0.97)"
          ],
          "decimals": 2,
          "pattern": "/.*/",
          "thresholds": [],
          "type": "number",
          "unit": "short"
        }
      ],
      "targets": [
        {
          "expr": "topk($TopLimit, avg(avg_over_time(vendor:coherence_memory_heap_after_gc_used{cluster=~\"$ClusterName\"}[$__range]) / avg_over_time(vendor:coherence_memory_heap_memory_usage_max{cluster=~\"$ClusterName\"}[$__range])) by (member))",
          "format": "table",
          "instant": true,
          "interval": "",
          "intervalFactor": 1,
          "legendFormat": "",
          "refId": "A"
        }
      ],
      "title": "Top $TopLimit Members - Memory Used % - Current Range",
      "transform": "table",
      "type": "table"
    },
    {
      "columns": [],
      "datasource": "Prometheus",
      "description": "The top  $TopLimit Members that have the greatest  Total GC Time over the current time range.",
      "fontSize": "100%",
      "gridPos": {
        "h": 6,
        "w": 8,
        "x": 0,
        "y": 30
      },
      "id": 74,
      "links": [],
      "pageSize": null,
      "scroll": true,
      "showHeader": true,
      "sort": {
        "col": null,
        "desc": false
      },
      "styles": [
        {
          "alias": "Time",
          "align": "auto",
          "dateFormat": "YYYY-MM-DD HH:mm:ss",
          "pattern": "Time",
          "type": "hidden"
        },
        {
          "alias": "Member Name",
          "align": "auto",
          "colorMode": null,
          "colors": [
            "rgba(245, 54, 54, 0.9)",
            "rgba(237, 129, 40, 0.89)",
            "rgba(50, 172, 45, 0.97)"
          ],
          "dateFormat": "YYYY-MM-DD HH:mm:ss",
          "decimals": 2,
          "link": true,
          "linkTooltip": "Drill down to member details for  ${__cell}",
          "linkUrl": "/d/coh-member-details?var-ClusterName=$ClusterName&var-MemberName=${__cell}",
          "mappingType": 1,
          "pattern": "member",
          "thresholds": [],
          "type": "string",
          "unit": "short"
        },
        {
          "alias": "Service",
          "align": "auto",
          "colorMode": null,
          "colors": [
            "rgba(245, 54, 54, 0.9)",
            "rgba(237, 129, 40, 0.89)",
            "rgba(50, 172, 45, 0.97)"
          ],
          "dateFormat": "YYYY-MM-DD HH:mm:ss",
          "decimals": 2,
          "mappingType": 1,
          "pattern": "name",
          "thresholds": [],
          "type": "string",
          "unit": "short"
        },
        {
          "alias": "Total GC Time",
          "align": "auto",
          "colorMode": null,
          "colors": [
            "rgba(245, 54, 54, 0.9)",
            "rgba(237, 129, 40, 0.89)",
            "rgba(50, 172, 45, 0.97)"
          ],
          "dateFormat": "YYYY-MM-DD HH:mm:ss",
          "decimals": 2,
          "mappingType": 1,
          "pattern": "Value",
          "thresholds": [],
          "type": "number",
          "unit": "ms"
        },
        {
          "alias": "",
          "align": "auto",
          "colorMode": null,
          "colors": [
            "rgba(245, 54, 54, 0.9)",
            "rgba(237, 129, 40, 0.89)",
            "rgba(50, 172, 45, 0.97)"
          ],
          "decimals": 2,
          "pattern": "/.*/",
          "thresholds": [],
          "type": "number",
          "unit": "short"
        }
      ],
      "targets": [
        {
          "expr": " topk($TopLimit,sum(delta(vendor:coherence_gc_collection_time{cluster=~\"$ClusterName\"}[$__range])) by (member)) > 0",
          "format": "table",
          "instant": true,
          "intervalFactor": 1,
          "legendFormat": "",
          "refId": "A"
        }
      ],
      "title": "Top $TopLimit Members - Total GC Time -  Current Range",
      "transform": "table",
      "type": "table"
    },
    {
      "columns": [],
      "datasource": "Prometheus",
      "description": "The top  $TopLimit Members that have the greatest change in the Task Count over the current time range.",
      "fontSize": "100%",
      "gridPos": {
        "h": 6,
        "w": 8,
        "x": 8,
        "y": 30
      },
      "id": 119,
      "links": [],
      "pageSize": null,
      "scroll": true,
      "showHeader": true,
      "sort": {
        "col": 3,
        "desc": true
      },
      "styles": [
        {
          "alias": "Time",
          "align": "auto",
          "dateFormat": "YYYY-MM-DD HH:mm:ss",
          "pattern": "Time",
          "type": "hidden"
        },
        {
          "alias": "Member",
          "align": "auto",
          "colorMode": null,
          "colors": [
            "rgba(245, 54, 54, 0.9)",
            "rgba(237, 129, 40, 0.89)",
            "rgba(50, 172, 45, 0.97)"
          ],
          "dateFormat": "YYYY-MM-DD HH:mm:ss",
          "decimals": 2,
          "link": true,
          "linkTooltip": "Drill down to member details for  ${__cell}",
          "linkUrl": "/d/coh-member-details?var-ClusterName=$ClusterName&var-MemberName=${__cell}",
          "mappingType": 1,
          "pattern": "member",
          "thresholds": [],
          "type": "string",
          "unit": "short"
        },
        {
          "alias": "Service",
          "align": "auto",
          "colorMode": null,
          "colors": [
            "rgba(245, 54, 54, 0.9)",
            "rgba(237, 129, 40, 0.89)",
            "rgba(50, 172, 45, 0.97)"
          ],
          "dateFormat": "YYYY-MM-DD HH:mm:ss",
          "decimals": 2,
          "mappingType": 1,
          "pattern": "name",
          "thresholds": [],
          "type": "string",
          "unit": "short"
        },
        {
          "alias": "Task Count",
          "align": "auto",
          "colorMode": null,
          "colors": [
            "rgba(245, 54, 54, 0.9)",
            "rgba(237, 129, 40, 0.89)",
            "rgba(50, 172, 45, 0.97)"
          ],
          "dateFormat": "YYYY-MM-DD HH:mm:ss",
          "decimals": 0,
          "mappingType": 1,
          "pattern": "Value",
          "thresholds": [],
          "type": "number",
          "unit": "none"
        },
        {
          "alias": "",
          "align": "auto",
          "colorMode": null,
          "colors": [
            "rgba(245, 54, 54, 0.9)",
            "rgba(237, 129, 40, 0.89)",
            "rgba(50, 172, 45, 0.97)"
          ],
          "decimals": 2,
          "pattern": "/.*/",
          "thresholds": [],
          "type": "number",
          "unit": "short"
        }
      ],
      "targets": [
        {
          "expr": " topk($TopLimit,sum(delta(vendor:coherence_service_task_count{cluster=~\"$ClusterName\"}[$__range])) by (member)) > 0",
          "format": "table",
          "instant": true,
          "intervalFactor": 1,
          "legendFormat": "",
          "refId": "A"
        }
      ],
      "title": "Top $TopLimit Members - Task Count -  Current Range",
      "transform": "table",
      "type": "table"
    },
    {
      "columns": [],
      "datasource": "Prometheus",
      "description": "The top  $TopLimit Services  that have the greatest change in the Task Count over the current time range.",
      "fontSize": "100%",
      "gridPos": {
        "h": 6,
        "w": 8,
        "x": 16,
        "y": 30
      },
      "id": 73,
      "links": [],
      "pageSize": null,
      "scroll": true,
      "showHeader": true,
      "sort": {
        "col": 3,
        "desc": true
      },
      "styles": [
        {
          "alias": "Time",
          "align": "auto",
          "dateFormat": "YYYY-MM-DD HH:mm:ss",
          "pattern": "Time",
          "type": "hidden"
        },
        {
          "alias": "Member",
          "align": "auto",
          "colorMode": null,
          "colors": [
            "rgba(245, 54, 54, 0.9)",
            "rgba(237, 129, 40, 0.89)",
            "rgba(50, 172, 45, 0.97)"
          ],
          "dateFormat": "YYYY-MM-DD HH:mm:ss",
          "decimals": 2,
          "mappingType": 1,
          "pattern": "member",
          "thresholds": [],
          "type": "string",
          "unit": "short"
        },
        {
          "alias": "Service",
          "align": "auto",
          "colorMode": null,
          "colors": [
            "rgba(245, 54, 54, 0.9)",
            "rgba(237, 129, 40, 0.89)",
            "rgba(50, 172, 45, 0.97)"
          ],
          "dateFormat": "YYYY-MM-DD HH:mm:ss",
          "decimals": 2,
          "link": true,
          "linkTooltip": "Drill down to service details for ${__cell}",
          "linkUrl": "/d/coh-service-details?var-ServiceName=${__cell}&var-ClusterName=$ClusterName",
          "mappingType": 1,
          "pattern": "name",
          "thresholds": [],
          "type": "string",
          "unit": "short"
        },
        {
          "alias": "Task Count",
          "align": "auto",
          "colorMode": null,
          "colors": [
            "rgba(245, 54, 54, 0.9)",
            "rgba(237, 129, 40, 0.89)",
            "rgba(50, 172, 45, 0.97)"
          ],
          "dateFormat": "YYYY-MM-DD HH:mm:ss",
          "decimals": 0,
          "mappingType": 1,
          "pattern": "Value",
          "thresholds": [],
          "type": "number",
          "unit": "none"
        },
        {
          "alias": "",
          "align": "auto",
          "colorMode": null,
          "colors": [
            "rgba(245, 54, 54, 0.9)",
            "rgba(237, 129, 40, 0.89)",
            "rgba(50, 172, 45, 0.97)"
          ],
          "decimals": 2,
          "pattern": "/.*/",
          "thresholds": [],
          "type": "number",
          "unit": "short"
        }
      ],
      "targets": [
        {
          "expr": " topk($TopLimit,sum(delta(vendor:coherence_service_task_count{cluster=~\"$ClusterName\"}[$__range])) by (name)) > 0",
          "format": "table",
          "instant": true,
          "interval": "",
          "intervalFactor": 1,
          "legendFormat": "",
          "refId": "A"
        }
      ],
      "title": "Top $TopLimit Services - Task Count - Current Range",
      "transform": "table",
      "type": "table"
    },
    {
      "aliasColors": {},
      "bars": true,
      "dashLength": 10,
      "dashes": false,
      "datasource": "Prometheus",
      "decimals": 0,
      "description": "Total task backlog per member.",
      "fill": 1,
      "fillGradient": 0,
      "gridPos": {
        "h": 8,
        "w": 8,
        "x": 0,
        "y": 36
      },
      "hiddenSeries": false,
      "id": 114,
      "legend": {
        "avg": false,
        "current": false,
        "hideZero": true,
        "max": false,
        "min": false,
        "show": true,
        "total": false,
        "values": false
      },
      "lines": false,
      "linewidth": 1,
      "links": [
        {
          "title": "Members Summary Dashboard",
          "url": "/d/coh-members-summary/members-summary-dashboard?$__url_time_range&$__all_variables"
        }
      ],
      "nullPointMode": "null as zero",
      "options": {
        "dataLinks": []
      },
      "percentage": false,
      "pointradius": 5,
      "points": false,
      "renderer": "flot",
      "seriesOverrides": [],
      "spaceLength": 10,
      "stack": false,
      "steppedLine": false,
      "targets": [
        {
          "expr": "sum(vendor:coherence_service_task_backlog{cluster=~\"$ClusterName\"}) by (member) > 0",
          "format": "time_series",
          "instant": false,
          "intervalFactor": 1,
          "legendFormat": "{{member}}",
          "refId": "A"
        }
      ],
      "thresholds": [],
      "timeFrom": null,
      "timeRegions": [],
      "timeShift": null,
      "title": "Task Backlog By Member",
      "tooltip": {
        "shared": true,
        "sort": 0,
        "value_type": "individual"
      },
      "type": "graph",
      "xaxis": {
        "buckets": null,
        "mode": "time",
        "name": null,
        "show": true,
        "values": []
      },
      "yaxes": [
        {
          "decimals": 0,
          "format": "short",
          "label": null,
          "logBase": 1,
          "max": null,
          "min": "0",
          "show": true
        },
        {
          "decimals": 0,
          "format": "short",
          "label": null,
          "logBase": 1,
          "max": null,
          "min": null,
          "show": false
        }
      ],
      "yaxis": {
        "align": false,
        "alignLevel": null
      }
    },
    {
      "aliasColors": {},
      "bars": false,
      "dashLength": 10,
      "dashes": false,
      "datasource": "Prometheus",
      "decimals": 0,
      "description": "Total task backlog by service.",
      "fill": 1,
      "fillGradient": 0,
      "gridPos": {
        "h": 8,
        "w": 8,
        "x": 8,
        "y": 36
      },
      "hiddenSeries": false,
      "id": 113,
      "legend": {
        "avg": false,
        "current": true,
        "hideZero": true,
        "max": true,
        "min": false,
        "show": true,
        "total": false,
        "values": true
      },
      "lines": true,
      "linewidth": 1,
      "links": [
        {
          "title": "Services Summary Dashboard",
          "url": "/d/coh-services-summary/services-summary-dashboard?$__url_time_range&$__all_variables"
        }
      ],
      "nullPointMode": "null",
      "options": {
        "dataLinks": []
      },
      "percentage": false,
      "pointradius": 5,
      "points": false,
      "renderer": "flot",
      "seriesOverrides": [],
      "spaceLength": 10,
      "stack": false,
      "steppedLine": false,
      "targets": [
        {
          "expr": "sum(vendor:coherence_service_task_backlog{cluster=~\"$ClusterName\"}) by (name)",
          "format": "time_series",
          "instant": false,
          "intervalFactor": 1,
          "legendFormat": "{{name}}",
          "refId": "A"
        }
      ],
      "thresholds": [],
      "timeFrom": null,
      "timeRegions": [],
      "timeShift": null,
      "title": "Task Backlog By Service",
      "tooltip": {
        "shared": true,
        "sort": 0,
        "value_type": "individual"
      },
      "type": "graph",
      "xaxis": {
        "buckets": null,
        "mode": "time",
        "name": null,
        "show": true,
        "values": []
      },
      "yaxes": [
        {
          "decimals": 0,
          "format": "short",
          "label": null,
          "logBase": 1,
          "max": null,
          "min": "0",
          "show": true
        },
        {
          "decimals": 0,
          "format": "short",
          "label": null,
          "logBase": 1,
          "max": null,
          "min": null,
          "show": false
        }
      ],
      "yaxis": {
        "align": false,
        "alignLevel": null
      }
    },
    {
      "aliasColors": {},
      "bars": false,
      "dashLength": 10,
      "dashes": false,
      "datasource": "Prometheus",
      "decimals": 0,
      "description": "Total Proxy Outgoing Byte Backlog by Service",
      "fill": 1,
      "fillGradient": 0,
      "gridPos": {
        "h": 8,
        "w": 8,
        "x": 16,
        "y": 36
      },
      "hiddenSeries": false,
      "id": 118,
      "legend": {
        "avg": false,
        "current": true,
        "hideZero": true,
        "max": true,
        "min": false,
        "show": true,
        "total": false,
        "values": true
      },
      "lines": true,
      "linewidth": 1,
      "links": [
        {
          "title": "Proxy Servers Summary Dashboard",
          "url": "/d/coh-proxy-services-summary/proxy-servers-summary-dashboard?$__url_time_range&$__all_variables"
        }
      ],
      "nullPointMode": "null",
      "options": {
        "dataLinks": []
      },
      "percentage": false,
      "pointradius": 5,
      "points": false,
      "renderer": "flot",
      "seriesOverrides": [],
      "spaceLength": 10,
      "stack": false,
      "steppedLine": false,
      "targets": [
        {
          "expr": "sum(vendor:coherence_connection_manager_outgoing_byte_backlog{cluster=~\"$ClusterName\"}) by (name)",
          "format": "time_series",
          "instant": false,
          "intervalFactor": 1,
          "legendFormat": "{{name}}",
          "refId": "A"
        }
      ],
      "thresholds": [],
      "timeFrom": null,
      "timeRegions": [],
      "timeShift": null,
      "title": "Proxy Outgoing Byte Backlog by Service",
      "tooltip": {
        "shared": true,
        "sort": 0,
        "value_type": "individual"
      },
      "type": "graph",
      "xaxis": {
        "buckets": null,
        "mode": "time",
        "name": null,
        "show": true,
        "values": []
      },
      "yaxes": [
        {
          "decimals": 0,
          "format": "decbytes",
          "label": null,
          "logBase": 1,
          "max": null,
          "min": "0",
          "show": true
        },
        {
          "decimals": 0,
          "format": "short",
          "label": null,
          "logBase": 1,
          "max": null,
          "min": null,
          "show": false
        }
      ],
      "yaxis": {
        "align": false,
        "alignLevel": null
      }
    },
    {
      "columns": [],
      "datasource": "Prometheus",
      "description": "Services that  have unbalanced partitions.",
      "fontSize": "100%",
      "gridPos": {
        "h": 6,
        "w": 12,
        "x": 0,
        "y": 44
      },
      "id": 52,
      "links": [],
      "pageSize": null,
      "scroll": true,
      "showHeader": true,
      "sort": {
        "col": 1,
        "desc": false
      },
      "styles": [
        {
          "alias": "Time",
          "align": "auto",
          "dateFormat": "YYYY-MM-DD HH:mm:ss",
          "pattern": "Time",
          "type": "hidden"
        },
        {
          "alias": "Unbalanced Partitions",
          "align": "auto",
          "colorMode": "cell",
          "colors": [
            "rgba(50, 172, 45, 0.97)",
            "rgba(237, 129, 40, 0.89)",
            "rgba(245, 54, 54, 0.9)"
          ],
          "dateFormat": "YYYY-MM-DD HH:mm:ss",
          "decimals": 0,
          "mappingType": 1,
          "pattern": "Value",
          "thresholds": [
            "-1",
            "0"
          ],
          "type": "number",
          "unit": "short"
        },
        {
          "alias": "Service Name",
          "align": "auto",
          "colorMode": null,
          "colors": [
            "rgba(245, 54, 54, 0.9)",
            "rgba(237, 129, 40, 0.89)",
            "rgba(50, 172, 45, 0.97)"
          ],
          "dateFormat": "YYYY-MM-DD HH:mm:ss",
          "decimals": 2,
          "link": true,
          "linkTargetBlank": false,
          "linkTooltip": "Drill down to service details for ${__cell}",
          "linkUrl": "/d/coh-service-details?var-ServiceName=${__cell}&var-ClusterName=$ClusterName",
          "mappingType": 1,
          "pattern": "name",
          "thresholds": [],
          "type": "number",
          "unit": "short"
        },
        {
          "alias": "",
          "align": "auto",
          "colorMode": null,
          "colors": [
            "rgba(245, 54, 54, 0.9)",
            "rgba(237, 129, 40, 0.89)",
            "rgba(50, 172, 45, 0.97)"
          ],
          "decimals": 2,
          "pattern": "/.*/",
          "thresholds": [],
          "type": "number",
          "unit": "short"
        }
      ],
      "targets": [
        {
          "expr": "avg(vendor:coherence_service_partitions_unbalanced{cluster=~\"$ClusterName\", type=~\"DistributedCache|FederatedCache\"}) by(name) > 0",
          "format": "table",
          "instant": true,
          "intervalFactor": 1,
          "legendFormat": "",
          "refId": "B"
        }
      ],
      "title": "Current Suspect Services - Unbalanced Partitions",
      "transform": "table",
      "type": "table"
    },
    {
      "columns": [],
      "datasource": "Prometheus",
      "description": "The top  $TopLimit Members that have the greatest change in sent and received messages over the current time range.",
      "fontSize": "100%",
      "gridPos": {
        "h": 6,
        "w": 12,
        "x": 12,
        "y": 44
      },
      "id": 75,
      "links": [],
      "pageSize": null,
      "scroll": true,
      "showHeader": true,
      "sort": {
        "col": 3,
        "desc": true
      },
      "styles": [
        {
          "alias": "Time",
          "align": "auto",
          "dateFormat": "YYYY-MM-DD HH:mm:ss",
          "pattern": "Time",
          "type": "hidden"
        },
        {
          "alias": "Member",
          "align": "auto",
          "colorMode": null,
          "colors": [
            "rgba(245, 54, 54, 0.9)",
            "rgba(237, 129, 40, 0.89)",
            "rgba(50, 172, 45, 0.97)"
          ],
          "dateFormat": "YYYY-MM-DD HH:mm:ss",
          "decimals": 2,
          "link": true,
          "linkTooltip": "Drill down to member details for  ${__cell}",
          "linkUrl": "/d/coh-member-details?var-ClusterName=$ClusterName&var-MemberName=${__cell}",
          "mappingType": 1,
          "pattern": "member",
          "thresholds": [],
          "type": "string",
          "unit": "short"
        },
        {
          "alias": "Service",
          "align": "auto",
          "colorMode": null,
          "colors": [
            "rgba(245, 54, 54, 0.9)",
            "rgba(237, 129, 40, 0.89)",
            "rgba(50, 172, 45, 0.97)"
          ],
          "dateFormat": "YYYY-MM-DD HH:mm:ss",
          "decimals": 2,
          "mappingType": 1,
          "pattern": "name",
          "thresholds": [],
          "type": "string",
          "unit": "short"
        },
        {
          "alias": "Network Messages",
          "align": "auto",
          "colorMode": null,
          "colors": [
            "rgba(245, 54, 54, 0.9)",
            "rgba(237, 129, 40, 0.89)",
            "rgba(50, 172, 45, 0.97)"
          ],
          "dateFormat": "YYYY-MM-DD HH:mm:ss",
          "decimals": 0,
          "mappingType": 1,
          "pattern": "Value",
          "thresholds": [],
          "type": "number",
          "unit": "none"
        },
        {
          "alias": "",
          "align": "auto",
          "colorMode": null,
          "colors": [
            "rgba(245, 54, 54, 0.9)",
            "rgba(237, 129, 40, 0.89)",
            "rgba(50, 172, 45, 0.97)"
          ],
          "decimals": 2,
          "pattern": "/.*/",
          "thresholds": [],
          "type": "number",
          "unit": "short"
        }
      ],
      "targets": [
        {
          "expr": "topk($TopLimit, sum(vendor:coherence_node_packets_sent{cluster=~\"$ClusterName\"} + vendor:coherence_node_packets_received{cluster=~\"$ClusterName\"}  - vendor:coherence_node_packets_sent{cluster=~\"$ClusterName\"} offset $__range -  vendor:coherence_node_packets_received{cluster=~\"$ClusterName\"} offset $__range) by (member))",
          "format": "table",
          "instant": true,
          "intervalFactor": 1,
          "legendFormat": "",
          "refId": "A"
        }
      ],
      "title": "Top $TopLimit Members - Network -  Current Range",
      "transform": "table",
      "type": "table"
    },
    {
      "columns": [],
      "datasource": "Prometheus",
      "description": "The current top $TopLimit caches, services and member with the highest Max Query Time.",
      "fontSize": "100%",
      "gridPos": {
        "h": 6,
        "w": 12,
        "x": 0,
        "y": 50
      },
      "id": 86,
      "links": [],
      "pageSize": null,
      "scroll": true,
      "showHeader": true,
      "sort": {
        "col": 4,
        "desc": true
      },
      "styles": [
        {
          "alias": "Time",
          "align": "auto",
          "dateFormat": "YYYY-MM-DD HH:mm:ss",
          "pattern": "Time",
          "type": "hidden"
        },
        {
          "alias": "Max Query Duration",
          "align": "auto",
          "colorMode": null,
          "colors": [
            "rgba(245, 54, 54, 0.9)",
            "rgba(237, 129, 40, 0.89)",
            "rgba(50, 172, 45, 0.97)"
          ],
          "dateFormat": "YYYY-MM-DD HH:mm:ss",
          "decimals": 2,
          "mappingType": 1,
          "pattern": "Value",
          "thresholds": [],
          "type": "number",
          "unit": "ms"
        },
        {
          "alias": "Member",
          "align": "auto",
          "colorMode": null,
          "colors": [
            "rgba(245, 54, 54, 0.9)",
            "rgba(237, 129, 40, 0.89)",
            "rgba(50, 172, 45, 0.97)"
          ],
          "dateFormat": "YYYY-MM-DD HH:mm:ss",
          "decimals": 2,
          "link": true,
          "linkTargetBlank": false,
          "linkTooltip": "Drill down to member details for  ${__cell}",
          "linkUrl": "/d/coh-member-details?var-ClusterName=$ClusterName&var-MemberName=${__cell}",
          "mappingType": 1,
          "pattern": "member",
          "thresholds": [],
          "type": "number",
          "unit": "short"
        },
        {
          "alias": "Service",
          "align": "auto",
          "colorMode": null,
          "colors": [
            "rgba(245, 54, 54, 0.9)",
            "rgba(237, 129, 40, 0.89)",
            "rgba(50, 172, 45, 0.97)"
          ],
          "dateFormat": "YYYY-MM-DD HH:mm:ss",
          "decimals": 2,
          "link": true,
          "linkTooltip": "",
          "linkUrl": "/d/coh-service-details?var-ServiceName=${__cell}&var-ClusterName=$ClusterName",
          "mappingType": 1,
          "pattern": "coherence_service",
          "thresholds": [],
          "type": "number",
          "unit": "short"
        },
        {
          "alias": "Cache",
          "align": "auto",
          "colorMode": null,
          "colors": [
            "rgba(245, 54, 54, 0.9)",
            "rgba(237, 129, 40, 0.89)",
            "rgba(50, 172, 45, 0.97)"
          ],
          "dateFormat": "YYYY-MM-DD HH:mm:ss",
          "decimals": 2,
          "link": true,
          "linkTooltip": "",
          "linkUrl": "/d/coh-cache-details?var-ClusterName=$ClusterName&var-ServiceName=${__cell_3}&var-CacheName=${__cell}&range=$__range",
          "mappingType": 1,
          "pattern": "cache",
          "thresholds": [],
          "type": "string",
          "unit": "short"
        },
        {
          "alias": "",
          "align": "auto",
          "colorMode": null,
          "colors": [
            "rgba(245, 54, 54, 0.9)",
            "rgba(237, 129, 40, 0.89)",
            "rgba(50, 172, 45, 0.97)"
          ],
          "decimals": 2,
          "pattern": "/.*/",
          "thresholds": [],
          "type": "number",
          "unit": "short"
        }
      ],
      "targets": [
        {
          "expr": "topk($TopLimit, sum(vendor:coherence_storage_max_query_duration_milis{cluster=~\"$ClusterName\"}) by (member, service, cache)) > 0",
          "format": "table",
          "instant": true,
          "intervalFactor": 1,
          "legendFormat": "",
          "refId": "A"
        }
      ],
      "title": "Current Top  $TopLimit Cache Max Query Times",
      "transform": "table",
      "type": "table"
    },
    {
      "columns": [],
      "datasource": "Prometheus",
      "description": "The current top $TopLimit nodes with the highest number of Non-Optimized Queries.",
      "fontSize": "100%",
      "gridPos": {
        "h": 6,
        "w": 12,
        "x": 12,
        "y": 50
      },
      "id": 85,
      "links": [],
      "pageSize": null,
      "scroll": true,
      "showHeader": true,
      "sort": {
        "col": 1,
        "desc": false
      },
      "styles": [
        {
          "alias": "Time",
          "align": "auto",
          "dateFormat": "YYYY-MM-DD HH:mm:ss",
          "pattern": "Time",
          "type": "hidden"
        },
        {
          "alias": "Max Query Duration",
          "align": "auto",
          "colorMode": null,
          "colors": [
            "rgba(245, 54, 54, 0.9)",
            "rgba(237, 129, 40, 0.89)",
            "rgba(50, 172, 45, 0.97)"
          ],
          "dateFormat": "YYYY-MM-DD HH:mm:ss",
          "decimals": 2,
          "mappingType": 1,
          "pattern": "Value",
          "thresholds": [],
          "type": "number",
          "unit": "ms"
        },
        {
          "alias": "Member",
          "align": "auto",
          "colorMode": null,
          "colors": [
            "rgba(245, 54, 54, 0.9)",
            "rgba(237, 129, 40, 0.89)",
            "rgba(50, 172, 45, 0.97)"
          ],
          "dateFormat": "YYYY-MM-DD HH:mm:ss",
          "decimals": 2,
          "link": true,
          "linkTargetBlank": false,
          "linkTooltip": "Drill down to member details for  ${__cell}",
          "linkUrl": "/d/coh-member-details?var-ClusterName=$ClusterName&var-MemberName=${__cell}",
          "mappingType": 1,
          "pattern": "member",
          "thresholds": [],
          "type": "number",
          "unit": "short"
        },
        {
          "alias": "Service",
          "align": "auto",
          "colorMode": null,
          "colors": [
            "rgba(245, 54, 54, 0.9)",
            "rgba(237, 129, 40, 0.89)",
            "rgba(50, 172, 45, 0.97)"
          ],
          "dateFormat": "YYYY-MM-DD HH:mm:ss",
          "decimals": 2,
          "link": true,
          "linkUrl": "/d/coh-service-details?var-ServiceName=${__cell}&var-ClusterName=$ClusterName",
          "mappingType": 1,
          "pattern": "coherence_service",
          "thresholds": [],
          "type": "number",
          "unit": "short"
        },
        {
          "alias": "Cache",
          "align": "auto",
          "colorMode": null,
          "colors": [
            "rgba(245, 54, 54, 0.9)",
            "rgba(237, 129, 40, 0.89)",
            "rgba(50, 172, 45, 0.97)"
          ],
          "dateFormat": "YYYY-MM-DD HH:mm:ss",
          "decimals": 2,
          "link": true,
          "linkTooltip": "",
          "linkUrl": "/d/coh-cache-details?var-ClusterName=$ClusterName&var-ServiceName=${__cell_3}&var-CacheName=${__cell}",
          "mappingType": 1,
          "pattern": "cache",
          "thresholds": [],
          "type": "string",
          "unit": "short"
        },
        {
          "alias": "",
          "align": "auto",
          "colorMode": null,
          "colors": [
            "rgba(245, 54, 54, 0.9)",
            "rgba(237, 129, 40, 0.89)",
            "rgba(50, 172, 45, 0.97)"
          ],
          "decimals": 2,
          "pattern": "/.*/",
          "thresholds": [],
          "type": "number",
          "unit": "short"
        }
      ],
      "targets": [
        {
          "expr": "topk($TopLimit, sum(vendor:coherence_storage_non_optimized_query_count{cluster=~\"$ClusterName\"}) by (member, service, cache))> 0",
          "format": "table",
          "instant": true,
          "intervalFactor": 1,
          "legendFormat": "",
          "refId": "A"
        }
      ],
      "title": "Current Top $TopLimit Non-Optimized Queries",
      "transform": "table",
      "type": "table"
    },
    {
      "aliasColors": {},
      "bars": true,
      "dashLength": 10,
      "dashes": false,
      "datasource": "Prometheus",
      "fill": 1,
      "fillGradient": 0,
      "gridPos": {
        "h": 8,
        "w": 12,
        "x": 0,
        "y": 56
      },
      "hiddenSeries": false,
      "id": 116,
      "legend": {
        "avg": false,
        "current": true,
        "hideZero": false,
        "max": true,
        "min": false,
        "show": true,
        "total": false,
        "values": true
      },
      "lines": false,
      "linewidth": 1,
      "links": [],
      "nullPointMode": "null",
      "options": {
        "dataLinks": []
      },
      "percentage": false,
      "pointradius": 5,
      "points": false,
      "renderer": "flot",
      "seriesOverrides": [],
      "spaceLength": 10,
      "stack": false,
      "steppedLine": false,
      "targets": [
        {
          "expr": "vendor:coherence_node_guard_recover_count{cluster=~\"$ClusterName\"} - vendor:coherence_node_guard_recover_count{cluster=~\"$ClusterName\"} offset $__interval ",
          "format": "time_series",
          "interval": "",
          "intervalFactor": 1,
          "legendFormat": "{{member}}",
          "refId": "A"
        }
      ],
      "thresholds": [],
      "timeFrom": null,
      "timeRegions": [],
      "timeShift": null,
      "title": "Guardian Recoveries",
      "tooltip": {
        "shared": true,
        "sort": 0,
        "value_type": "individual"
      },
      "type": "graph",
      "xaxis": {
        "buckets": null,
        "mode": "time",
        "name": null,
        "show": true,
        "values": []
      },
      "yaxes": [
        {
          "decimals": 0,
          "format": "none",
          "label": null,
          "logBase": 1,
          "max": null,
          "min": "0",
          "show": true
        },
        {
          "format": "short",
          "label": null,
          "logBase": 1,
          "max": null,
          "min": null,
          "show": false
        }
      ],
      "yaxis": {
        "align": false,
        "alignLevel": null
      }
    },
    {
      "aliasColors": {},
      "bars": true,
      "dashLength": 10,
      "dashes": false,
      "datasource": "Prometheus",
      "fill": 1,
      "fillGradient": 0,
      "gridPos": {
        "h": 8,
        "w": 12,
        "x": 12,
        "y": 56
      },
      "hiddenSeries": false,
      "id": 117,
      "legend": {
        "avg": false,
        "current": true,
        "hideZero": false,
        "max": true,
        "min": false,
        "show": true,
        "total": false,
        "values": true
      },
      "lines": false,
      "linewidth": 1,
      "links": [],
      "nullPointMode": "null",
      "options": {
        "dataLinks": []
      },
      "percentage": false,
      "pointradius": 5,
      "points": false,
      "renderer": "flot",
      "seriesOverrides": [],
      "spaceLength": 10,
      "stack": false,
      "steppedLine": false,
      "targets": [
        {
          "expr": "vendor:coherence_node_guard_terminate_count{cluster=~\"$ClusterName\"} - vendor:coherence_node_guard_terminate_count{cluster=~\"$ClusterName\"} offset $__interval",
          "format": "time_series",
          "interval": "",
          "intervalFactor": 1,
          "legendFormat": "{{member}}",
          "refId": "A"
        }
      ],
      "thresholds": [],
      "timeFrom": null,
      "timeRegions": [],
      "timeShift": null,
      "title": "Guardian Terminations",
      "tooltip": {
        "shared": true,
        "sort": 0,
        "value_type": "individual"
      },
      "type": "graph",
      "xaxis": {
        "buckets": null,
        "mode": "time",
        "name": null,
        "show": true,
        "values": []
      },
      "yaxes": [
        {
          "decimals": 0,
          "format": "none",
          "label": null,
          "logBase": 1,
          "max": null,
          "min": "0",
          "show": true
        },
        {
          "format": "short",
          "label": null,
          "logBase": 1,
          "max": null,
          "min": null,
          "show": false
        }
      ],
      "yaxis": {
        "align": false,
        "alignLevel": null
      }
    }
  ],
  "refresh": "30s",
  "schemaVersion": 22,
  "style": "dark",
  "tags": [],
  "templating": {
    "list": [
      {
        "allValue": null,
        "current": {
        },
        "datasource": "Prometheus",
        "definition": "",
        "hide": 0,
        "includeAll": false,
        "index": -1,
        "label": "Cluster Name",
        "multi": false,
        "name": "ClusterName",
        "options": [],
        "query": "label_values(vendor:coherence_cluster_size, cluster)",
        "refresh": 1,
        "regex": "",
        "skipUrlSync": false,
        "sort": 1,
        "tagValuesQuery": "",
        "tags": [],
        "tagsQuery": "",
        "type": "query",
        "useTags": false
      },
      {
        "allValue": null,
        "current": {
        },
        "datasource": "Prometheus",
        "definition": "",
        "hide": 2,
        "includeAll": false,
        "index": -1,
        "label": "Coherence Version",
        "multi": false,
        "name": "CoherenceVersion",
        "options": [],
        "query": "label_values(vendor:coherence_cluster_size{cluster=~\"$ClusterName\"}, version)",
        "refresh": 1,
        "regex": "",
        "skipUrlSync": false,
        "sort": 0,
        "tagValuesQuery": "",
        "tags": [],
        "tagsQuery": "",
        "type": "query",
        "useTags": false
      },
      {
        "allValue": null,
        "current": {
          "selected": true,
          "text": "All",
          "value": "$__all"
        },
        "datasource": "Prometheus",
        "definition": "",
        "hide": 2,
        "includeAll": true,
        "index": -1,
        "label": "Services",
        "multi": false,
        "name": "Services",
        "options": [],
        "query": "label_values(vendor:coherence_service_request_max_duration{cluster=~\"$ClusterName\"}, name)",
        "refresh": 1,
        "regex": "",
        "skipUrlSync": false,
        "sort": 0,
        "tagValuesQuery": "",
        "tags": [],
        "tagsQuery": "",
        "type": "query",
        "useTags": false
      },
      {
        "allValue": null,
        "current": {
          "text": "All",
          "value": [
            "$__all"
          ]
        },
        "datasource": "Prometheus",
        "definition": "",
        "hide": 2,
        "includeAll": true,
        "index": -1,
        "label": "Caches",
        "multi": true,
        "name": "Caches",
        "options": [],
        "query": "label_values(vendor:coherence_cache_size{cluster=~\"$ClusterName\"}, name) ",
        "refresh": 1,
        "regex": "",
        "skipUrlSync": false,
        "sort": 0,
        "tagValuesQuery": "",
        "tags": [],
        "tagsQuery": "",
        "type": "query",
        "useTags": false
      },
      {
        "allValue": null,
        "current": {
          "selected": true,
          "text": "3",
          "value": "3"
        },
        "hide": 0,
        "includeAll": false,
        "label": "Top N Limit",
        "multi": false,
        "name": "TopLimit",
        "options": [
          {
            "selected": false,
            "text": "1",
            "value": "1"
          },
          {
            "selected": true,
            "text": "3",
            "value": "3"
          },
          {
            "selected": false,
            "text": "5",
            "value": "5"
          },
          {
            "selected": false,
            "text": "10",
            "value": "10"
          },
          {
            "selected": false,
            "text": "15",
            "value": "15"
          }
        ],
        "query": "1,3,5,10,15",
        "skipUrlSync": false,
        "type": "custom"
      }
    ]
  },
  "time": {
    "from": "now-30m",
    "to": "now"
  },
  "timepicker": {
    "refresh_intervals": [
      "5s",
      "10s",
      "30s",
      "1m",
      "5m",
      "15m",
      "30m",
      "1h",
      "2h",
      "1d"
    ],
    "time_options": [
      "5m",
      "15m",
      "1h",
      "6h",
      "12h",
      "24h",
      "2d",
      "7d",
      "30d"
    ]
  },
  "timezone": "",
  "title": "Coherence Dashboard Main",
  "uid": "coh-main",
  "variables": {
    "list": []
  },
  "version": 1
}
